README.rst
setup.py
papis_dmenu/__init__.py
papis_dmenu/config.py
papis_dmenu/dmenu.py
papis_dmenu.egg-info/PKG-INFO
papis_dmenu.egg-info/SOURCES.txt
papis_dmenu.egg-info/dependency_links.txt
papis_dmenu.egg-info/entry_points.txt
papis_dmenu.egg-info/requires.txt
papis_dmenu.egg-info/top_level.txt