Metadata-Version: 2.1
Name: papis-dmenu
Version: 0.3
Summary: dmenu based inerface for papis
Home-page: https://github.com/papis/papis-dmenu
Author: Alejandro Gallo
Author-email: aamsgallo@gmail.com
License: GPLv3
Keywords: papis,dmenu,bibtex,management,cli,biliography
Platform: linux
Platform: osx
Classifier: Environment :: Console
Classifier: Environment :: Console :: Curses
Classifier: Intended Audience :: Developers
Classifier: Intended Audience :: System Administrators
Classifier: License :: OSI Approved :: GNU General Public License v3 (GPLv3)
Classifier: Operating System :: MacOS
Classifier: Operating System :: POSIX
Classifier: Operating System :: Unix
Classifier: Programming Language :: Python :: 3.3
Classifier: Programming Language :: Python :: 3.4
Classifier: Programming Language :: Python :: 3.5
Classifier: Programming Language :: Python :: 3.6
Classifier: Topic :: Utilities
Provides-Extra: develop
